{
  "web": {
    "client_id": "0oasigs92ISH2DeFa4x6",
    "client_secret": "Yh0yDl9PqMMx9s0dZtJE165rgcOr8Aisvc0vku7Q",
    "auth_uri": "https://dev-969069.okta.com/oauth2/default/v1/authorize",
    "token_uri": "https://dev-969069.okta.com/oauth2/default/v1/token",
    "issuer": "https://dev-969069.okta.com/oauth2/default",
    "userinfo_uri": "https://dev-969069.okta.com/oauth2/default/userinfo",
    "token_introspection_uri": "https://dev-969069.okta.com/oauth2/default/v1/introspect",
    "redirect_uris": [
      "http://localhost:8000/oidc/callback"
    ]
  }
}